Workbook

Sheet 0_Resumen
A1: ESTRATEGIA INMOBILIARIA 2026-2036 — Resumen ejecutivo
A2: 6 escenarios del brief de José Luis (28/07/2026). Fórmulas vivas — cambia los inputs y esto se recalcula.
A4: ⚠️ Dato clave confirmado hoy: reforma San Antonio (1→3 dormitorios) = 3.000€ solo materiales, José Luis pone la mano de obra. Sin penalización por dejar el alquiler de Ibiza antes de 2033. Escenario 6 = rehipotecar SA para invertir en Alicante (no para comprar vivienda principal).
A8: 1. ¿Cuál genera más patrimonio a 20 años?
A9: =INDEX({"E1";"E2";"E3";"E4";"E5";"E6"},MATCH(MAX('3_Proyeccion'!C26:H26),'3_Proyeccion'!C26:H26,0))&" — "&TEXT(MAX('3_Proyeccion'!C26:H26),"#,##0")&"€"
A11: 2. ¿Cuál genera más dinero neto mensual (cash flow)?
A12: =INDEX({"E1";"E2";"E3";"E4";"E5";"E6"},MATCH(MAX('3_Proyeccion'!C4:H4),'3_Proyeccion'!C4:H4,0))&" — "&TEXT(MAX('3_Proyeccion'!C4:H4),"#,##0")&"€/mes"
A14: 3. ¿Cuál tiene menor riesgo?
A15: E2 (vivir en San Antonio, no alquilar nada) — sin gestión de inquilinos, sin vacancia, sin depender de que Ibiza permita subarrendar, sin financiación nueva. Es la opción con cero riesgo operativo o legal.
A17: 4. ¿Cuál requiere menos trabajo?
A18: E2, igual que en riesgo — cero gestión. El que más trabajo pide es E4 (habitaciones en SA con José Luis viviendo lejos, en Ibiza) y E3 (gestionar el subarriendo de Ibiza a distancia).
A20: 5. ¿Qué haría un inversor profesional?
A21: Miraría rentabilidad ajustada a riesgo, no solo el número más alto. E5 (reformar SA, 3.000€ de inversión) tiene el mejor payback porque la inversión es mínima y la mano de obra es gratis — probablemente el movimiento más eficiente antes de decidir nada más grande. E6 depende de la financiación de Alicante, que ya sabemos que no es viable solo con nóminas (ver modelo de esta mañana) — un inversor profesional no lo ejecutaría sin resolver antes esa financiación.
A23: 6. ¿Qué oportunidades no estamos considerando?
A24: Ver pestaña 5_Oportunidades: coliving, alquiler temporal/estacional (encaja bien con la estacionalidad de Ibiza), nómadas digitales en temporada baja, alquiler corporativo.
A26: 7. ¿Cuál es el plan óptimo para los próximos 24 meses?
A27: Paso 1 (ya, barato y sin riesgo): hacer la reforma de SA (3.000€, tú pones mano de obra) — te abre la opción de habitaciones sin comprometerte a nada más. Paso 2: cuando tengas llaves de SA (tras desahucio), decide entre alquilar tradicional (E1) o habitaciones (E4) con el modelo ya construido esta mañana (SANANTONIO_TRAD_VS_HAB). Paso 3: NO muevas la ampliación de 230k a Alicante (E6) hasta resolver la financiación — sigue la regla del mes (tasación + FEIN primero). Vivir en SA (E2) solo tiene sentido si prefieres cero gestión sobre maximizar ingreso — es una decisión de estilo de vida, no solo de dinero.

Sheet 1_Inputs
A1: ESTRATEGIA INMOBILIARIA 2026-2036 — Inputs
A2: Rojo = dato real pendiente de confirmar. Amarillo = supuesto editable. Blanco = dato confirmado.
A4: VIVIENDA IBIZA (alquilada, donde vive hoy)
A5: Alquiler actual (€/mes) | B5: 2000
A6: Contrato vigente hasta | B6: 2033
A7: ¿Permite subarrendar habitaciones? (confirmar documentalmente) | B7: SÍ (sin confirmar por escrito)
A8: Habitación 1 subarriendo (€/mes) | B8: 950
A9: Habitación 2 subarriendo (€/mes) | B9: 850
A10: Habitación 3 subarriendo (€/mes) | B10: 800
A11: Gastos gestión/suministros extra si subarrienda (€/mes) | B11: 150
A13: PISO SAN ANTONIO (propiedad)
A14: Hipoteca (€/mes) | B14: 360
A15: Valor estimado (BBVA, no oficial) (€) | B15: 350000
A16: Superficie (m²) | B16: 68
A17: Alquiler completo, 1 dormitorio (€/mes bruto) | B17: 1850
A18: Vacancia anual tradicional (%) | B18: 0.05
A19: Seguro impago tradicional (% renta anual) | B19: 0.035
A20: Coste reforma redistribución a 3 dormitorios (€) — confirmado José Luis: 1 tabique + 2 puertas, mano de obra propia, solo materiales | B20: 3000
A21: Habitación grande tras reforma (€/mes) | B21: 800
A22: Habitación pequeña 1 tras reforma (€/mes) | B22: 650
A23: Habitación pequeña 2 tras reforma (€/mes) | B23: 650
A24: Vacancia anual habitaciones (%, estacional Ibiza) | B24: 0.2
A25: Gestión habitaciones — % sobre renta bruta (José Luis no está allí) | B25: 0.15
... A27: Incremento de tasación estimado tras reforma (%) | B27: 0.1
A29: AMPLIACIÓN HIPOTECA SAN ANTONIO (para comprar otra vivienda)
A30: Importe ampliación (€) | B30: 230000
A31: Cuota mensual ampliación (€) — ver modelo Alicante ya calculado | B31: 1151.43
A32: Liquidez neta disponible (€) — ver modelo Alicante ya calculado | B32: 165810
A34: COMUNES / FISCALES
A35: IRPF marginal aplicable a renta neta (%) | B35: 0.3
A36: Revalorización anual inmuebles asumida (%) | B36: 0.03
A37: Tipo de descuento para VAN (%) | B37: 0.05

Sheet 2_Escenarios
B1: 6 ESCENARIOS — Cash flow mensual
B3: Concepto | C3: E1: Ibiza + alquilar SA tradicional | D3: E2: Mudarse a SA, sin alquilar | E3: E3: Mudarse a SA + subarrendar Ibiza | F3: E4: Ibiza + alquilar SA habitaciones | G3: E5: Reformar SA antes de rehipotecar | H3: E6: Rehipotecar SA para comprar otra vivienda
B4: Ingreso San Antonio tradicional, renta bruta (€/mes) | C4: ='1_Inputs'!$B$17 | D4: 0 | E4: 0 | F4: =F14 | G4: =F14 | H4: 0
B5: Vacancia + seguro impago (€/mes) | C5: =C4*('1_Inputs'!$B$18+'1_Inputs'!$B$19) | D5: 0 | E5: 0 | F5: 0 | G5: 0 | H5: 0
B6: Ingreso neto San Antonio (€/mes) | C6: =C4-C5 | D6: 0 | E6: 0 | F6: =F4 | G6: =G4 | H6: 0
B7: Alquiler Ibiza (€/mes) | C7: =-'1_Inputs'!$B$5 | D7: 0 | E7: =-'1_Inputs'!$B$5 | F7: =-'1_Inputs'!$B$5 | G7: =-'1_Inputs'!$B$5 | H7: =H26
B8: Hipoteca San Antonio (€/mes) | C8: =-'1_Inputs'!$B$14 | D8: =-'1_Inputs'!$B$14 | E8: =-'1_Inputs'!$B$14 | F8: =-'1_Inputs'!$B$14 | G8: =-'1_Inputs'!$B$14 | H8: 0
B9: CASH FLOW MENSUAL E1 (€) | C9: =C6+C7+C8 | D9: =D6+D7+D8 | E9: =E6+E7+E8+('1_Inputs'!$B$8+'1_Inputs'!$B$9+'1_Inputs'!$B$10-'1_Inputs'!$B$11) | F9: =F6+F7+F8 | G9: =G6+G7+G8 | H9: =H25-H24+H7
B11: — Detalle Escenario 4 (habitaciones SA) —
B12: Renta bruta habitaciones SA (€/mes) | F12: ='1_Inputs'!$B$21+'1_Inputs'!$B$22+'1_Inputs'!$B$23
B13: Vacancia + gestión + suministros (€/mes) | F13: =F12*'1_Inputs'!$B$24+F12*'1_Inputs'!$B$25+'1_Inputs'!$B$26
B14: Ingreso neto habitaciones SA (€/mes) | F14: =F12-F13
B16: — Detalle Escenario 5 (reforma como inversión) —
B17: Coste reforma (€) | G17: ='1_Inputs'!$B$20
B18: Valor SA antes (€) | G18: ='1_Inputs'!$B$15
B19: Incremento tasación tras reforma (%) | G19: ='1_Inputs'!$B$27
B20: Incremento de valor (€) | G20: =G18*G19
B21: ROI de la reforma sobre tasación (%) | G21: =G20/G17
B23: — Detalle Escenario 6 (rehipotecar SA 230k → invertir en edificio Alicante, mejor escenario) —
B24: Cuota ampliación SA 230k (€/mes) | H24: ='1_Inputs'!$B$31
B25: Cash flow neto mensual edificio Alicante (mejor escenario, ya calculado esta mañana en modelo Alicante, tras su propia hipoteca) (€/mes) | H25: 911.71
B26: Sigue pagando alquiler Ibiza igual (no se muda) (€/mes) | H26: =-'1_Inputs'!$B$5
H28: Nota: sigue viviendo en Ibiza (mismo alquiler), no compra vivienda principal. La inversión es en Alicante, financiada con la rehipoteca de SA. Cifra de cash flow Alicante viene del modelo ALICANTE_MODELO_2026-07-24.xlsx, Escenario C, ya construido esta mañana — no se repite el cálculo completo aquí.

Sheet 3_Proyeccion
B1: PROYECCIÓN 5 / 10 / 20 AÑOS — Cash flow acumulado + patrimonio
B3: Concepto | C3: E1: Ibiza + alquilar SA tradicional | D3: E2: Mudarse a SA, sin alquilar | E3: E3: Mudarse a SA + subarrendar Ibiza | F3: E4: Ibiza + alquilar SA habitaciones | G3: E5: Reformar SA antes de rehipotecar | H3: E6: Rehipotecar SA para comprar otra vivienda
B4: Cash flow mensual (€) — ref. 2_Escenarios | C4: ='2_Escenarios'!C9 | D4: ='2_Escenarios'!D9 | E4: ='2_Escenarios'!E9 | F4: ='2_Escenarios'!F9 | G4: ='2_Escenarios'!G9 | H4: ='2_Escenarios'!H9
B5: Cash flow anual (€) | C5: =C4*12 | D5: =D4*12 | E5: =E4*12 | F5: =F4*12 | G5: =G4*12 | H5: =H4*12
B7: CASH FLOW ACUMULADO (sin revalorización)
B8: Acumulado 5 años (€) | C8: =C5*5 | D8: =D5*5 | E8: =E5*5 | F8: =F5*5 | G8: =G5*5 | H8: =H5*5
B9: Acumulado 10 años (€) | C9: =C5*10 | D9: =D5*10 | E9: =E5*10 | F9: =F5*10 | G9: =G5*10 | H9: =H5*10
B10: Acumulado 20 años (€) | C10: =C5*20 | D10: =D5*20 | E10: =E5*20 | F10: =F5*20 | G10: =G5*20 | H10: =H5*20
B12: REVALORIZACIÓN INMUEBLES (patrimonio no realizado)
B13: Valor San Antonio hoy (€) — E6 usa valor tras ampliación, mismo inmueble | C13: ='1_Inputs'!$B$15 | D13: ='1_Inputs'!$B$15 | E13: ='1_Inputs'!$B$15 | F13: ='1_Inputs'!$B$15 | G13: ='1_Inputs'!$B$15 | H13: ='1_Inputs'!$B$15
B14: Revalorización anual asumida (%) | C14: ='1_Inputs'!$B$36 | D14: ='1_Inputs'!$B$36 | E14: ='1_Inputs'!$B$36 | F14: ='1_Inputs'!$B$36 | G14: ='1_Inputs'!$B$36 | H14: ='1_Inputs'!$B$36
B15: Ganancia patrimonial no realizada, San Antonio, 5 años (€) | C15: =C13*((1+C14)^5-1) | D15: =D13*((1+D14)^5-1) | E15: =E13*((1+E14)^5-1) | F15: =F13*((1+F14)^5-1) | G15: =G13*((1+G14)^5-1) | H15: =H13*((1+H14)^5-1)
B16: Ganancia patrimonial no realizada, San Antonio, 10 años (€) | C16: =C13*((1+C14)^10-1) | D16: =D13*((1+D14)^10-1) | E16: =E13*((1+E14)^10-1) | F16: =F13*((1+F14)^10-1) | G16: =G13*((1+G14)^10-1) | H16: =H13*((1+H14)^10-1)
B17: Ganancia patrimonial no realizada, San Antonio, 20 años (€) | C17: =C13*((1+C14)^20-1) | D17: =D13*((1+D14)^20-1) | E17: =E13*((1+E14)^20-1) | F17: =F13*((1+F14)^20-1) | G17: =G13*((1+G14)^20-1) | H17: =H13*((1+H14)^20-1)
B18: Extra E5: incremento valor por reforma (€, una vez, ya en el año en que se hace) | G18: ='2_Escenarios'!G20
B19: a 5 años (edificio Alicante 350k, no vivienda principal) | H19: =350000*((1+'1_Inputs'!$B$36)^5-1)
B20: a 10 años (edificio Alicante 350k) | H20: =350000*((1+'1_Inputs'!$B$36)^10-1)
B21: a 20 años (edificio Alicante 350k) | H21: =350000*((1+'1_Inputs'!$B$36)^20-1)
B23: PATRIMONIO TOTAL GENERADO (cash flow acumulado + revalorización)
B24: PATRIMONIO A 5 AÑOS (€) | C24: =C8+C15 | D24: =D8+D15 | E24: =E8+E15 | F24: =F8+F15 | G24: =G8+G15+G18 | H24: =H8+H15+H19
B25: PATRIMONIO A 10 AÑOS (€) | C25: =C9+C16 | D25: =D9+D16 | E25: =E9+E16 | F25: =F9+F16 | G25: =G9+G16+G18 | H25: =H9+H16+H20
B26: PATRIMONIO A 20 AÑOS (€) | C26: =C10+C17 | D26: =D10+D17 | E26: =E10+E17 | F26: =F10+F17 | G26: =G10+G17+G18 | H26: =H10+H17+H21
B29: INVERSIÓN Y RETORNO — Escenario 5 (reforma SA), única inversión de capital propio real
B30: Inversión inicial: coste reforma (€) | G30: =-'2_Escenarios'!G17
B31: Flujo incremental anual atribuible a la reforma (E4 vs E1) (€/año) | G31: ='3_Proyeccion'!F5-'3_Proyeccion'!C5
B32: Payback simple (años) | G32: =IF(G31>0,-G30/G31,"N/A")
B33: Flujos año 0-10 para TIR/VAN (tabla auxiliar abajo) →
B34: Año | C34: 0 | D34: 1 | E34: 2 | F34: 3 | G34: 4 | H34: 5 | I34: 6 | J34: 7 | K34: 8 | L34: 9 | M34: 10
B35: Flujo (€) | C35: =G30 | D35: =G31 | E35: =G31 | F35: =G31 | G35: =G31 | H35: =G31 | I35: =G31 | J35: =G31 | K35: =G31 | L35: =G31 | M35: =G31+'2_Escenarios'!G20
B37: VAN a 10 años, tasa de descuento (€) | G37: =C35+NPV('1_Inputs'!$B$37,D35:M35)
B38: TIR a 10 años (%) | G38: =IRR(C35:M35)
B40: Escenario 6 no tiene una inversión de capital propio clásica (financiado al 100% vía deuda) — su cash flow y patrimonio ya están arriba. Para el desglose de gastos de compra de la vivienda principal (ITP, notaría, registro), ver el Excel de esta mañana (7_Decision del modelo Alicante).

Sheet 4_Legal_Fiscal
A1: ASPECTOS LEGALES Y FISCALES — checklist, no son cálculos
A3: SUBARRIENDO IBIZA
A4: El contrato actual de Ibiza dice que permite subarrendar habitaciones — PENDIENTE confirmarlo documentalmente (leer la cláusula exacta o preguntar al casero por escrito). Sin esto, Escenario 3 tiene riesgo real de incumplimiento de contrato.
A6: CONTRATO IBIZA — SALIDA ANTICIPADA
A7: Si te mudas a San Antonio antes de 2033, hay que revisar si el contrato tiene penalización por dejarlo antes de plazo o si basta con preaviso — PENDIENTE de tu respuesta / de leer la cláusula de duración y desistimiento (normalmente LAU permite desistir a partir del 6º mes con 30 días de preaviso, pero puede haber indemnización pactada de hasta 1 mensualidad por año que falte).
A9: REFORMA SAN ANTONIO — LICENCIA
A10: Redistribuir un dormitorio en tres (tabiques nuevos) normalmente es obra menor y con comunicación al ayuntamiento (Sant Antoni) basta, no licencia de obra mayor — pero si toca instalaciones (fontanería, electricidad para una 3ª habitación) puede requerir más trámite. Confirmar con el ayuntamiento antes de tabicar.
A12: HABITABILIDAD
A13: Para alquilar por habitaciones, cada habitación debe cumplir mínimos de habitabilidad (ventilación, superficie mínima ~6m² dormitorio individual en normativa balear) — verificar que las 3 habitaciones resultantes cumplen tras la redistribución.
A15: SUBARRIENDO — RÉGIMEN LEGAL
A16: El alquiler por habitaciones en vivienda propia (San Antonio) no es 'subarriendo' sino arrendamiento directo de habitaciones — distinto régimen del subarriendo de la vivienda de Ibiza (que si es de alquiler, sería subarriendo real y necesita autorización expresa del propietario, art. 8 LAU).
A18: SEGURO DE HOGAR / IMPAGO
... A25: Si compra una 2ª vivienda para vivir (Escenario 6), San Antonio deja de ser vivienda habitual a efectos fiscales si se alquila — revisar impacto en posibles deducciones o en el IBI/recargos de vivienda vacía si no se alquila.

Sheet 5_Oportunidades
A1: OPORTUNIDADES ADICIONALES — exploratorio, no cuantificado
A3: Coliving
A4: San Antonio con 3 habitaciones + zonas comunes podría orientarse a coliving (perfil profesional/nómada, contratos algo más largos que turístico, rentas 700-900€/hab en Ibiza según demanda). Requiere más gestión y mobiliario/decoración que habitaciones sueltas.
A6: Alquiler temporal (media/larga estacionalidad)
A7: Alquiler de 1-6 meses a trabajadores de temporada (hostelería, sanidad) — rentas más altas que anual, menos que turístico diario, sin necesidad de licencia turística. Encaja bien con la estacionalidad de Ibiza que ya penaliza el modelo de habitaciones anual.
A9: Nómadas digitales
A10: Perfil similar a coliving pero estancias 1-3 meses, rentas premium en temporada baja (oct-may) cuando la demanda de vivienda tradicional cae en Ibiza. Podría suavizar la vacancia estacional del 20% asumida en el modelo de habitaciones.
A12: Empresas (alquiler corporativo)
A13: Alquilar San Antonio completo a una empresa para alojar trabajadores desplazados (turismo, construcción) — renta estable tipo tradicional pero algo superior, sin gestión de rotación de habitaciones.
A15: Compra mediante sociedad (SL)
A16: Si el patrimonio crece (ver plan 1M€ ya en marcha), estructurar futuras compras vía SL puede tener ventajas fiscales (IS 15-25% vs IRPF marginal más alto) — ya se está explorando en el proyecto plan-financiero-2026/informe-negocios-escalables-2026.md. No repetir el análisis aquí, son el mismo tema.
A18: Estrategias fiscales
... A22: Ver plan 1M€ a 10 años ya en marcha (flips en Alicante) — no se repite aquí, es el mismo plan, ver [[../plan-financiero-2026/plan-1M-10anos|plan 1M€]].
