Workbook

Sheet 1_Inputs
A1: SAN ANTONIO — Tradicional vs Habitaciones — Inputs
A2: Amarillo = supuesto editable. Rojo = pendiente de decidir/confirmar. Basado en cifras del brief 26/07/2026.
A4: TRADICIONAL (contrato LAU larga duración)
A5: Renta bruta mensual (€) | B5: 1200
A6: Vacancia anual (%) — rotación baja | B6: 0.05
A7: Suministros a cargo de (inquilino=0€, propietario=importe) | B7: 0
A8: Gestión delegada — % sobre renta bruta (remoto, mínima) | B8: 0
A9: Seguro impago — % sobre renta bruta anual (estándar mercado) | B9: 0.035
A10: % renta computable por el banco en DSTI (LAU larga duración) | B10: 0.65
A12: HABITACIONES (3 hab., Código Civil)
A13: Renta bruta mensual total (3 hab. × 550-650€) (€) | B13: 1750
A14: Vacancia anual (%) — alta, estacional Ibiza | B14: 0.2
A15: Suministros a cargo del propietario (€/mes) | B15: 175
A16: Gestión delegada — % sobre renta bruta (presencial: limpieza, rotación, check-in/out; José Luis estará en Alicante, no puede hacerlo él) | B16: 0.15
A17: Seguro impago disponible (SÍ/NO) | B17: NO — muchas aseguradoras no cubren habitaciones o cobertura peor
A18: Seguro impago — % sobre renta bruta anual, SI estuviera disponible (referencia) | B18: 0.07
A19: % renta computable por el banco en DSTI (habitaciones, muchos bancos computan poco/nada) | B19: 0.1
A21: COMUNES
A22: Ingresos nómina combinados (€/mes) — referencia, ver modelo Alicante | B22: 3800
A23: Tipo interés hipoteca referencia (para traducir margen DSTI a capital) (%) | B23: 0.0375
A24: Plazo hipoteca referencia (años) | B24: 25

Sheet 2_Comparativa
A1: COMPARATIVA 3 AÑOS — Tradicional vs Habitaciones
A3: Concepto | B3: Tradicional | C3: Habitaciones
A4: Renta bruta mensual (€) | B4: ='1_Inputs'!$B$5 | C4: ='1_Inputs'!$B$13
A5: Renta bruta anual (€) | B5: =B4*12 | C5: =C4*12
A6: Vacancia anual (%) | B6: ='1_Inputs'!$B$6 | C6: ='1_Inputs'!$B$14
A7: Pérdida por vacancia (€/año) | B7: =B5*B6 | C7: =C5*C6
A8: Suministros (€/año) | B8: ='1_Inputs'!$B$7*12 | C8: ='1_Inputs'!$B$15*12
A9: Gestión delegada (€/año) | B9: =B5*'1_Inputs'!$B$8 | C9: =C5*'1_Inputs'!$B$16
A10: Seguro impago (€/año) | B10: =B5*'1_Inputs'!$B$9 | C10: =IF('1_Inputs'!$B$17="SÍ",C5*'1_Inputs'!$B$18,0)
A11: NETO ANUAL (€) | B11: =B5-B7-B8-B9-B10 | C11: =C5-C7-C8-C9-C10
A12: NETO 3 AÑOS (€) | B12: =B11*3 | C12: =C11*3
A13: Neto mensual medio (€/mes) | B13: =B11/12 | C13: =C11/12
A14: DIFERENCIA vs otra opción, 3 años (€) | B14: =B12-C12 | C14: =C12-B12
A16: IMPACTO EN CAPACIDAD DE FINANCIACIÓN (el factor decisivo para el plan 1M€)
A17: % renta computable por el banco en DSTI | B17: ='1_Inputs'!$B$10 | C17: ='1_Inputs'!$B$19
A18: Ingreso extra computable en DSTI (€/mes) | B18: =B4*B17 | C18: =C4*C17
A19: Capital hipotecable adicional que desbloquea (€) | B19: =PV('1_Inputs'!$B$23/12,'1_Inputs'!$B$24*12,-B18) | C19: =PV('1_Inputs'!$B$23/12,'1_Inputs'!$B$24*12,-C18)
A20: DIFERENCIA capital hipotecable (€) | B20: =B19-C19
A22: Otros factores no monetarios (del brief): legal (habitaciones = Código Civil, desahucio algo más ágil pero no absoluto), seguro de impago (habitaciones: muchas aseguradoras no cubren o cobertura peor — riesgo sin colchón), timing (decisión real con llaves en mano, el desahucio puede tardar 6-10 meses).
A26: CONCLUSIÓN
A27: ="Cash flow 3 años: Tradicional "&TEXT(B12,"#,##0")&"€ vs Habitaciones "&TEXT(C12,"#,##0")&"€ (dif "&TEXT(B14,"#,##0")&"€). Capacidad de financiación: Tradicional desbloquea "&TEXT(B19,"#,##0")&"€ vs Habitaciones "&TEXT(C19,"#,##0")&"€ (dif "&TEXT(B20,"#,##0")&"€). "&IF(B12>C12,"Tradicional gana en cash flow. ","Habitaciones gana en cash flow. ")&IF(B19>C19,"Tradicional gana también en capacidad de financiación — con el plan 1M€ dependiendo de financiación, esto pesa más que el cash flow.","Habitaciones gana también en capacidad de financiación.")
